[
  {
    "id": "card-1766135199266-g8w7096t8",
    "type": "qa",
    "sourceContentId": "1766135199264-vf629dfp0",
    "sourceFile": "9.备忘/tag.md",
    "anchorLink": "[[tag#^extract-1766135199264-31xe00]]",
    "front": "黄色",
    "back": "事实/定义",
    "deck": "9.备忘",
    "tags": [],
    "scheduling": {
      "interval": 4,
      "ease": 2.5,
      "due": 1766501796249,
      "lapses": 0,
      "reps": 1,
      "state": "review"
    },
    "stats": {
      "totalReviews": 1,
      "correctCount": 1,
      "averageTime": 9.876,
      "lastReview": 1766156196249,
      "difficulty": 0.19999999999999998
    },
    "metadata": {
      "createdAt": 1766135199266,
      "updatedAt": 1766156196249
    }
  },
  {
    "id": "card-1766135199269-tavcom483",
    "type": "qa",
    "sourceContentId": "1766135199264-zuj1udqvg",
    "sourceFile": "9.备忘/tag.md",
    "anchorLink": "[[tag#^extract-1766135199264-iemcgc]]",
    "front": "橙色",
    "back": "不太懂",
    "deck": "9.备忘",
    "tags": [],
    "scheduling": {
      "interval": 4,
      "ease": 2.5,
      "due": 1766501822014,
      "lapses": 0,
      "reps": 1,
      "state": "review"
    },
    "stats": {
      "totalReviews": 1,
      "correctCount": 1,
      "averageTime": 25.761,
      "lastReview": 1766156222014,
      "difficulty": 0.19999999999999998
    },
    "metadata": {
      "createdAt": 1766135199269,
      "updatedAt": 1766156222014
    }
  },
  {
    "id": "card-1766135199270-enmo0do3i",
    "type": "qa",
    "sourceContentId": "1766135199264-9g2kxwl5k",
    "sourceFile": "9.备忘/tag.md",
    "anchorLink": "[[tag#^extract-1766135199264-qmpqa0]]",
    "front": "绿色",
    "back": "方法/技巧",
    "deck": "9.备忘",
    "tags": [],
    "scheduling": {
      "interval": 4,
      "ease": 2.5,
      "due": 1766503519640,
      "lapses": 0,
      "reps": 1,
      "state": "review"
    },
    "stats": {
      "totalReviews": 1,
      "correctCount": 1,
      "averageTime": 11.384,
      "lastReview": 1766157919640,
      "difficulty": 0.19999999999999998
    },
    "metadata": {
      "createdAt": 1766135199270,
      "updatedAt": 1766157919640
    }
  },
  {
    "id": "card-1766135199271-600cgmuo5",
    "type": "qa",
    "sourceContentId": "1766135199264-thxpwejn4",
    "sourceFile": "9.备忘/tag.md",
    "anchorLink": "[[tag#^extract-1766135199264-ab2d0y]]",
    "front": "蓝色",
    "back": "作者观点",
    "deck": "9.备忘",
    "tags": [],
    "scheduling": {
      "interval": 4,
      "ease": 2.5,
      "due": 1766503562735,
      "lapses": 0,
      "reps": 1,
      "state": "review"
    },
    "stats": {
      "totalReviews": 1,
      "correctCount": 1,
      "averageTime": 43.09,
      "lastReview": 1766157962735,
      "difficulty": 0.19999999999999998
    },
    "metadata": {
      "createdAt": 1766135199271,
      "updatedAt": 1766157962735
    }
  },
  {
    "id": "card-1766135199271-v37caompv",
    "type": "qa",
    "sourceContentId": "1766135199264-3eic6c570",
    "sourceFile": "9.备忘/tag.md",
    "anchorLink": "[[tag#^extract-1766135199264-lw7n3z]]",
    "front": "红色",
    "back": "存疑",
    "deck": "9.备忘",
    "tags": [],
    "scheduling": {
      "interval": 3,
      "ease": 2.5,
      "due": 1766578307384,
      "lapses": 0,
      "reps": 2,
      "state": "review"
    },
    "stats": {
      "totalReviews": 2,
      "correctCount": 2,
      "averageTime": 8.035,
      "lastReview": 1766319107384,
      "difficulty": 0.2
    },
    "metadata": {
      "createdAt": 1766135199271,
      "updatedAt": 1766319107384
    }
  },
  {
    "id": "card-1766135199272-3ovvttidd",
    "type": "qa",
    "sourceContentId": "1766135199264-5dq63sy0l",
    "sourceFile": "9.备忘/tag.md",
    "anchorLink": "[[tag#^extract-1766135199264-rf936z]]",
    "front": "紫色",
    "back": "启发/洞察",
    "deck": "9.备忘",
    "tags": [],
    "scheduling": {
      "interval": 4,
      "ease": 2.5,
      "due": 1766505942789,
      "lapses": 0,
      "reps": 1,
      "state": "review"
    },
    "stats": {
      "totalReviews": 1,
      "correctCount": 1,
      "averageTime": 2375.971,
      "lastReview": 1766160342789,
      "difficulty": 0.19999999999999998
    },
    "metadata": {
      "createdAt": 1766135199272,
      "updatedAt": 1766160342789
    }
  },
  {
    "id": "card-1766135199272-e1b7cu8vv",
    "type": "qa",
    "sourceContentId": "1766135199264-6icfphm85",
    "sourceFile": "9.备忘/tag.md",
    "anchorLink": "[[tag#^extract-1766135199264-44r2tm]]",
    "front": "金色",
    "back": "重要概念",
    "deck": "9.备忘",
    "tags": [],
    "scheduling": {
      "interval": 4,
      "ease": 2.5,
      "due": 1766505955048,
      "lapses": 0,
      "reps": 1,
      "state": "review"
    },
    "stats": {
      "totalReviews": 1,
      "correctCount": 1,
      "averageTime": 12.253,
      "lastReview": 1766160355048,
      "difficulty": 0.19999999999999998
    },
    "metadata": {
      "createdAt": 1766135199272,
      "updatedAt": 1766160355048
    }
  }
]